outlookutility/__init__.py
outlookutility/default_table_style.py
outlookutility/display_email.py
outlookutility/display_email_with_attachments.py
outlookutility/email_with_attachments.py
outlookutility/email_without_attachment.py
outlookutility/multi_table_style.py
outlookutility/notify_error.py
outlookutility-1.4.dist-info/LICENSE
outlookutility-1.4.dist-info/METADATA
outlookutility-1.4.dist-info/WHEEL
outlookutility-1.4.dist-info/top_level.txt
outlookutility-1.4.dist-info/RECORD
