Metadata-Version: 2.1
Name: outlookutility
Version: 1.4
Summary: Outlook email automation functions
Home-page: https://github.com/MattDJensen/Outlook_Utility_Package
Author: Matthew Jensen
Author-email: matt@matthewjensen.dev
License: MIT
Download-URL: https://github.com/MattDJensen/Outlook_Utility_Package/archive/1.4.tar.gz
Platform: UNKNOWN
Classifier: License :: OSI Approved :: MIT License
Classifier: Programming Language :: Python :: 3
Classifier: Programming Language :: Python :: 3.8
Classifier: Operating System :: Microsoft :: Windows :: Windows 10
Requires-Python: >=3.6
Requires-Dist: pywin32
